remla24_team7_app/app.py
remla24_team7_app-0.1.0.dist-info/METADATA
remla24_team7_app-0.1.0.dist-info/WHEEL
remla24_team7_app-0.1.0.dist-info/RECORD
